virtual_fs/__init__.py
virtual_fs/main.py
virtual_fs/assets/example.txt
virtual_fs/cli/mount.py
virtual_fs-1.0.25.dist-info/licenses/LICENSE
virtual_fs-1.0.25.dist-info/METADATA
virtual_fs-1.0.25.dist-info/WHEEL
virtual_fs-1.0.25.dist-info/entry_points.txt
virtual_fs-1.0.25.dist-info/top_level.txt
virtual_fs-1.0.25.dist-info/RECORD
