Metadata-Version: 2.4
Name: virtual_fs
Version: 1.0.25
Summary: virtual file system for python, api level virtual mounting
Home-page: https://github.com/zackees/virtual-fs
Maintainer: Zachary Vorhies
License: BSD 3-Clause License
Keywords: template-python-cmd
Classifier: Programming Language :: Python :: 3
Requires-Python: >=3.10
License-File: LICENSE
Requires-Dist: rclone-api>=1.5.73
Dynamic: home-page
Dynamic: license-file
Dynamic: maintainer
